mailbandit/__init__.py
mailbandit/distilbert.py
mailbandit/main.py
mailbandit/train.py
mail_bandit-0.1.3.dist-info/METADATA
mail_bandit-0.1.3.dist-info/WHEEL
mail_bandit-0.1.3.dist-info/entry_points.txt
mail_bandit-0.1.3.dist-info/top_level.txt
mail_bandit-0.1.3.dist-info/RECORD
