Metadata-Version: 2.4
Name: mail_bandit
Version: 0.1.3
Summary: Mail Bandit is a fast, lightweight tool that classifies emails into five categories using DistilBERT and XGBoost.
Home-page: https://github.com/yourusername/mail-bandit
Author: Jabez Gershon Aldrin
Author-email: Jabez123jaze@gmail.com
License: MIT
Classifier: Programming Language :: Python :: 3
Classifier: License :: OSI Approved :: MIT License
Classifier: Operating System :: OS Independent
Requires-Python: >=3.7
Requires-Dist: transformers
Requires-Dist: scikit-learn
Requires-Dist: pandas
Requires-Dist: joblib
Dynamic: author
Dynamic: author-email
Dynamic: classifier
Dynamic: description
Dynamic: description-content-type
Dynamic: home-page
Dynamic: requires-dist
Dynamic: requires-python
Dynamic: summary
